{
  "title": "Clinical and Counseling Psychologists",
  "slug": "clinical-and-counseling-psychologists",
  "socCode": "19-3033",
  "dataYear": 2024,
  "typicalEducation": null,
  "workExperience": null,
  "onJobTraining": null,
  "jobOutlookPercent": null,
  "jobOutlookLabel": null,
  "national": {
    "totalEmployment": 72190,
    "meanHourly": 51.37,
    "meanAnnual": 106850,
    "medianHourly": 46.07,
    "medianAnnual": 95830,
    "pct10Hourly": 24.26,
    "pct25Hourly": 32.44,
    "pct75Hourly": 63.23,
    "pct90Hourly": 81.8,
    "pct10Annual": 50470,
    "pct25Annual": 67470,
    "pct75Annual": 131510,
    "pct90Annual": 170150
  },
  "states": [
    {
      "state": "Alabama",
      "stateSlug": "alabama",
      "stateAbbreviation": "AL",
      "totalEmployment": 360,
      "medianAnnual": 100320,
      "meanAnnual": 110180,
      "pct10Annual": 55600,
      "pct90Annual": 173410,
      "locationQuotient": 0.37
    },
    {
      "state": "Alaska",
      "stateSlug": "alaska",
      "stateAbbreviation": "AK",
      "totalEmployment": 80,
      "medianAnnual": 105870,
      "meanAnnual": 111840,
      "pct10Annual": 39990,
      "pct90Annual": 157610,
      "locationQuotient": 0.5
    },
    {
      "state": "Arizona",
      "stateSlug": "arizona",
      "stateAbbreviation": "AZ",
      "totalEmployment": 1140,
      "medianAnnual": 106970,
      "meanAnnual": 111730,
      "pct10Annual": 58010,
      "pct90Annual": 168850,
      "locationQuotient": 0.76
    },
    {
      "state": "Arkansas",
      "stateSlug": "arkansas",
      "stateAbbreviation": "AR",
      "totalEmployment": 510,
      "medianAnnual": null,
      "meanAnnual": null,
      "pct10Annual": null,
      "pct90Annual": null,
      "locationQuotient": 0.85
    },
    {
      "state": "California",
      "stateSlug": "california",
      "stateAbbreviation": "CA",
      "totalEmployment": 11900,
      "medianAnnual": 114520,
      "meanAnnual": 124720,
      "pct10Annual": 59990,
      "pct90Annual": 189540,
      "locationQuotient": 1.41
    },
    {
      "state": "Colorado",
      "stateSlug": "colorado",
      "stateAbbreviation": "CO",
      "totalEmployment": 1940,
      "medianAnnual": 126260,
      "meanAnnual": 129500,
      "pct10Annual": 62240,
      "pct90Annual": 209270,
      "locationQuotient": 1.43
    },
    {
      "state": "Connecticut",
      "stateSlug": "connecticut",
      "stateAbbreviation": "CT",
      "totalEmployment": 660,
      "medianAnnual": null,
      "meanAnnual": null,
      "pct10Annual": null,
      "pct90Annual": null,
      "locationQuotient": 0.84
    },
    {
      "state": "Delaware",
      "stateSlug": "delaware",
      "stateAbbreviation": "DE",
      "totalEmployment": 190,
      "medianAnnual": 109120,
      "meanAnnual": 108440,
      "pct10Annual": 63360,
      "pct90Annual": 139550,
      "locationQuotient": 0.86
    },
    {
      "state": "District of Columbia",
      "stateSlug": "district-of-columbia",
      "stateAbbreviation": "DC",
      "totalEmployment": 260,
      "medianAnnual": null,
      "meanAnnual": null,
      "pct10Annual": null,
      "pct90Annual": null,
      "locationQuotient": 0.78
    },
    {
      "state": "Florida",
      "stateSlug": "florida",
      "stateAbbreviation": "FL",
      "totalEmployment": 3230,
      "medianAnnual": 84020,
      "meanAnnual": 92010,
      "pct10Annual": 44450,
      "pct90Annual": 163030,
      "locationQuotient": 0.7
    },
    {
      "state": "Georgia",
      "stateSlug": "georgia",
      "stateAbbreviation": "GA",
      "totalEmployment": 1210,
      "medianAnnual": 51210,
      "meanAnnual": 74140,
      "pct10Annual": 18970,
      "pct90Annual": 159140,
      "locationQuotient": 0.53
    },
    {
      "state": "Hawaii",
      "stateSlug": "hawaii",
      "stateAbbreviation": "HI",
      "totalEmployment": 300,
      "medianAnnual": 108840,
      "meanAnnual": 110900,
      "pct10Annual": 74880,
      "pct90Annual": 137940,
      "locationQuotient": 1.04
    },
    {
      "state": "Idaho",
      "stateSlug": "idaho",
      "stateAbbreviation": "ID",
      "totalEmployment": 370,
      "medianAnnual": 74820,
      "meanAnnual": 93220,
      "pct10Annual": 43100,
      "pct90Annual": 140280,
      "locationQuotient": 0.94
    },
    {
      "state": "Illinois",
      "stateSlug": "illinois",
      "stateAbbreviation": "IL",
      "totalEmployment": 3470,
      "medianAnnual": 97470,
      "meanAnnual": 106360,
      "pct10Annual": 44150,
      "pct90Annual": 170450,
      "locationQuotient": 1.22
    },
    {
      "state": "Indiana",
      "stateSlug": "indiana",
      "stateAbbreviation": "IN",
      "totalEmployment": 1630,
      "medianAnnual": 80770,
      "meanAnnual": 91840,
      "pct10Annual": 56980,
      "pct90Annual": 134770,
      "locationQuotient": 1.09
    },
    {
      "state": "Iowa",
      "stateSlug": "iowa",
      "stateAbbreviation": "IA",
      "totalEmployment": 760,
      "medianAnnual": 98580,
      "meanAnnual": 102560,
      "pct10Annual": 57190,
      "pct90Annual": 164160,
      "locationQuotient": 1.04
    },
    {
      "state": "Kansas",
      "stateSlug": "kansas",
      "stateAbbreviation": "KS",
      "totalEmployment": 350,
      "medianAnnual": 61800,
      "meanAnnual": 65270,
      "pct10Annual": 30530,
      "pct90Annual": 100390,
      "locationQuotient": 0.52
    },
    {
      "state": "Kentucky",
      "stateSlug": "kentucky",
      "stateAbbreviation": "KY",
      "totalEmployment": 850,
      "medianAnnual": 116480,
      "meanAnnual": 126740,
      "pct10Annual": 49990,
      "pct90Annual": 202900,
      "locationQuotient": 0.91
    },
    {
      "state": "Louisiana",
      "stateSlug": "louisiana",
      "stateAbbreviation": "LA",
      "totalEmployment": 370,
      "medianAnnual": 67470,
      "meanAnnual": 88950,
      "pct10Annual": 45080,
      "pct90Annual": 121770,
      "locationQuotient": 0.41
    },
    {
      "state": "Maine",
      "stateSlug": "maine",
      "stateAbbreviation": "ME",
      "totalEmployment": 180,
      "medianAnnual": 97630,
      "meanAnnual": 114470,
      "pct10Annual": 73180,
      "pct90Annual": 213060,
      "locationQuotient": 0.61
    },
    {
      "state": "Maryland",
      "stateSlug": "maryland",
      "stateAbbreviation": "MD",
      "totalEmployment": 1680,
      "medianAnnual": 104480,
      "meanAnnual": 109990,
      "pct10Annual": 61940,
      "pct90Annual": 151280,
      "locationQuotient": 1.31
    },
    {
      "state": "Massachusetts",
      "stateSlug": "massachusetts",
      "stateAbbreviation": "MA",
      "totalEmployment": 3470,
      "medianAnnual": 87060,
      "meanAnnual": 102440,
      "pct10Annual": 52870,
      "pct90Annual": 160950,
      "locationQuotient": 2.03
    },
    {
      "state": "Michigan",
      "stateSlug": "michigan",
      "stateAbbreviation": "MI",
      "totalEmployment": 2650,
      "medianAnnual": 80030,
      "meanAnnual": 88810,
      "pct10Annual": 58030,
      "pct90Annual": 138490,
      "locationQuotient": 1.29
    },
    {
      "state": "Minnesota",
      "stateSlug": "minnesota",
      "stateAbbreviation": "MN",
      "totalEmployment": 1490,
      "medianAnnual": 102650,
      "meanAnnual": 98260,
      "pct10Annual": 38620,
      "pct90Annual": 137220,
      "locationQuotient": 1.09
    },
    {
      "state": "Mississippi",
      "stateSlug": "mississippi",
      "stateAbbreviation": "MS",
      "totalEmployment": 200,
      "medianAnnual": 92390,
      "meanAnnual": 95140,
      "pct10Annual": 48660,
      "pct90Annual": 115730,
      "locationQuotient": 0.37
    },
    {
      "state": "Missouri",
      "stateSlug": "missouri",
      "stateAbbreviation": "MO",
      "totalEmployment": 1490,
      "medianAnnual": 86340,
      "meanAnnual": 90480,
      "pct10Annual": 34580,
      "pct90Annual": 131520,
      "locationQuotient": 1.09
    },
    {
      "state": "Montana",
      "stateSlug": "montana",
      "stateAbbreviation": "MT",
      "totalEmployment": 180,
      "medianAnnual": null,
      "meanAnnual": null,
      "pct10Annual": null,
      "pct90Annual": null,
      "locationQuotient": 0.77
    },
    {
      "state": "Nevada",
      "stateSlug": "nevada",
      "stateAbbreviation": "NV",
      "totalEmployment": 510,
      "medianAnnual": 103510,
      "meanAnnual": 110520,
      "pct10Annual": 65910,
      "pct90Annual": 159800,
      "locationQuotient": 0.72
    },
    {
      "state": "New Hampshire",
      "stateSlug": "new-hampshire",
      "stateAbbreviation": "NH",
      "totalEmployment": 390,
      "medianAnnual": 52510,
      "meanAnnual": 66140,
      "pct10Annual": 38030,
      "pct90Annual": 118090,
      "locationQuotient": 1.21
    },
    {
      "state": "New Jersey",
      "stateSlug": "new-jersey",
      "stateAbbreviation": "NJ",
      "totalEmployment": 2850,
      "medianAnnual": 110190,
      "meanAnnual": 128400,
      "pct10Annual": 52960,
      "pct90Annual": 217260,
      "locationQuotient": 1.43
    },
    {
      "state": "New Mexico",
      "stateSlug": "new-mexico",
      "stateAbbreviation": "NM",
      "totalEmployment": 220,
      "medianAnnual": 73860,
      "meanAnnual": 87710,
      "pct10Annual": 48860,
      "pct90Annual": 153130,
      "locationQuotient": 0.56
    },
    {
      "state": "New York",
      "stateSlug": "new-york",
      "stateAbbreviation": "NY",
      "totalEmployment": 7190,
      "medianAnnual": 99910,
      "meanAnnual": 112980,
      "pct10Annual": 61000,
      "pct90Annual": 162570,
      "locationQuotient": 1.61
    },
    {
      "state": "North Carolina",
      "stateSlug": "north-carolina",
      "stateAbbreviation": "NC",
      "totalEmployment": 2420,
      "medianAnnual": 91840,
      "meanAnnual": 99940,
      "pct10Annual": 54130,
      "pct90Annual": 142120,
      "locationQuotient": 1.05
    },
    {
      "state": "North Dakota",
      "stateSlug": "north-dakota",
      "stateAbbreviation": "ND",
      "totalEmployment": 150,
      "medianAnnual": 109110,
      "meanAnnual": 105240,
      "pct10Annual": 60460,
      "pct90Annual": 148610,
      "locationQuotient": 0.75
    },
    {
      "state": "Ohio",
      "stateSlug": "ohio",
      "stateAbbreviation": "OH",
      "totalEmployment": 1360,
      "medianAnnual": 102290,
      "meanAnnual": 104420,
      "pct10Annual": 45720,
      "pct90Annual": 160210,
      "locationQuotient": 0.53
    },
    {
      "state": "Oklahoma",
      "stateSlug": "oklahoma",
      "stateAbbreviation": "OK",
      "totalEmployment": 360,
      "medianAnnual": 91140,
      "meanAnnual": 97350,
      "pct10Annual": 35990,
      "pct90Annual": 133810,
      "locationQuotient": 0.45
    },
    {
      "state": "Oregon",
      "stateSlug": "oregon",
      "stateAbbreviation": "OR",
      "totalEmployment": 440,
      "medianAnnual": 132550,
      "meanAnnual": 129110,
      "pct10Annual": 98110,
      "pct90Annual": 157540,
      "locationQuotient": 0.47
    },
    {
      "state": "Pennsylvania",
      "stateSlug": "pennsylvania",
      "stateAbbreviation": "PA",
      "totalEmployment": 3850,
      "medianAnnual": 90450,
      "meanAnnual": 103980,
      "pct10Annual": 54990,
      "pct90Annual": 170860,
      "locationQuotient": 1.37
    },
    {
      "state": "Rhode Island",
      "stateSlug": "rhode-island",
      "stateAbbreviation": "RI",
      "totalEmployment": 470,
      "medianAnnual": 101820,
      "meanAnnual": 103670,
      "pct10Annual": 55670,
      "pct90Annual": 138490,
      "locationQuotient": 2.01
    },
    {
      "state": "South Dakota",
      "stateSlug": "south-dakota",
      "stateAbbreviation": "SD",
      "totalEmployment": 100,
      "medianAnnual": 85790,
      "meanAnnual": 87040,
      "pct10Annual": 60860,
      "pct90Annual": 118280,
      "locationQuotient": 0.46
    },
    {
      "state": "Tennessee",
      "stateSlug": "tennessee",
      "stateAbbreviation": "TN",
      "totalEmployment": 780,
      "medianAnnual": 92320,
      "meanAnnual": 103190,
      "pct10Annual": 59500,
      "pct90Annual": 148840,
      "locationQuotient": 0.51
    },
    {
      "state": "Texas",
      "stateSlug": "texas",
      "stateAbbreviation": "TX",
      "totalEmployment": 3410,
      "medianAnnual": 72320,
      "meanAnnual": 83830,
      "pct10Annual": 37900,
      "pct90Annual": 136380,
      "locationQuotient": 0.53
    },
    {
      "state": "Utah",
      "stateSlug": "utah",
      "stateAbbreviation": "UT",
      "totalEmployment": 1000,
      "medianAnnual": 88990,
      "meanAnnual": 94070,
      "pct10Annual": 36860,
      "pct90Annual": 141390,
      "locationQuotient": 1.25
    },
    {
      "state": "Vermont",
      "stateSlug": "vermont",
      "stateAbbreviation": "VT",
      "totalEmployment": 160,
      "medianAnnual": 79550,
      "meanAnnual": 97220,
      "pct10Annual": 53340,
      "pct90Annual": 148490,
      "locationQuotient": 1.15
    },
    {
      "state": "Virginia",
      "stateSlug": "virginia",
      "stateAbbreviation": "VA",
      "totalEmployment": null,
      "medianAnnual": 87110,
      "meanAnnual": 105480,
      "pct10Annual": 60120,
      "pct90Annual": 201760,
      "locationQuotient": null
    },
    {
      "state": "Washington",
      "stateSlug": "washington",
      "stateAbbreviation": "WA",
      "totalEmployment": 980,
      "medianAnnual": 115050,
      "meanAnnual": 125270,
      "pct10Annual": 72540,
      "pct90Annual": 165820,
      "locationQuotient": 0.59
    },
    {
      "state": "West Virginia",
      "stateSlug": "west-virginia",
      "stateAbbreviation": "WV",
      "totalEmployment": 650,
      "medianAnnual": 70540,
      "meanAnnual": 88540,
      "pct10Annual": 35450,
      "pct90Annual": 155560,
      "locationQuotient": 1.98
    },
    {
      "state": "Wisconsin",
      "stateSlug": "wisconsin",
      "stateAbbreviation": "WI",
      "totalEmployment": 980,
      "medianAnnual": 103860,
      "meanAnnual": 117050,
      "pct10Annual": 64030,
      "pct90Annual": 174450,
      "locationQuotient": 0.72
    },
    {
      "state": "Wyoming",
      "stateSlug": "wyoming",
      "stateAbbreviation": "WY",
      "totalEmployment": 60,
      "medianAnnual": 79890,
      "meanAnnual": 79970,
      "pct10Annual": 54280,
      "pct90Annual": 105510,
      "locationQuotient": 0.49
    }
  ]
}