{
  "title": "Labor Relations Specialists",
  "slug": "labor-relations-specialists",
  "socCode": "13-1075",
  "dataYear": 2024,
  "typicalEducation": null,
  "workExperience": null,
  "onJobTraining": null,
  "jobOutlookPercent": null,
  "jobOutlookLabel": null,
  "national": {
    "totalEmployment": 64590,
    "meanHourly": 46.7,
    "meanAnnual": 97130,
    "medianHourly": 44.95,
    "medianAnnual": 93500,
    "pct10Hourly": 23.98,
    "pct25Hourly": 32.54,
    "pct75Hourly": 59.18,
    "pct90Hourly": 73.77,
    "pct10Annual": 49880,
    "pct25Annual": 67670,
    "pct75Annual": 123090,
    "pct90Annual": 153440
  },
  "states": [
    {
      "state": "Alabama",
      "stateSlug": "alabama",
      "stateAbbreviation": "AL",
      "totalEmployment": 510,
      "medianAnnual": 56360,
      "meanAnnual": 56650,
      "pct10Annual": 19130,
      "pct90Annual": 102440,
      "locationQuotient": 0.58
    },
    {
      "state": "Alaska",
      "stateSlug": "alaska",
      "stateAbbreviation": "AK",
      "totalEmployment": 150,
      "medianAnnual": 124770,
      "meanAnnual": 109660,
      "pct10Annual": 74070,
      "pct90Annual": 149940,
      "locationQuotient": 1.13
    },
    {
      "state": "Arizona",
      "stateSlug": "arizona",
      "stateAbbreviation": "AZ",
      "totalEmployment": 470,
      "medianAnnual": 76820,
      "meanAnnual": 88390,
      "pct10Annual": 53940,
      "pct90Annual": 116580,
      "locationQuotient": 0.35
    },
    {
      "state": "Arkansas",
      "stateSlug": "arkansas",
      "stateAbbreviation": "AR",
      "totalEmployment": 200,
      "medianAnnual": 53450,
      "meanAnnual": 68000,
      "pct10Annual": 31200,
      "pct90Annual": 117150,
      "locationQuotient": 0.37
    },
    {
      "state": "California",
      "stateSlug": "california",
      "stateAbbreviation": "CA",
      "totalEmployment": 9170,
      "medianAnnual": 105320,
      "meanAnnual": 116120,
      "pct10Annual": 50490,
      "pct90Annual": 168730,
      "locationQuotient": 1.21
    },
    {
      "state": "Colorado",
      "stateSlug": "colorado",
      "stateAbbreviation": "CO",
      "totalEmployment": 410,
      "medianAnnual": 82120,
      "meanAnnual": 92750,
      "pct10Annual": 53970,
      "pct90Annual": 151500,
      "locationQuotient": 0.34
    },
    {
      "state": "Connecticut",
      "stateSlug": "connecticut",
      "stateAbbreviation": "CT",
      "totalEmployment": 1150,
      "medianAnnual": 96710,
      "meanAnnual": 100000,
      "pct10Annual": 44270,
      "pct90Annual": 171490,
      "locationQuotient": 1.63
    },
    {
      "state": "Delaware",
      "stateSlug": "delaware",
      "stateAbbreviation": "DE",
      "totalEmployment": 270,
      "medianAnnual": 91910,
      "meanAnnual": 92170,
      "pct10Annual": 55870,
      "pct90Annual": 126040,
      "locationQuotient": 1.36
    },
    {
      "state": "District of Columbia",
      "stateSlug": "district-of-columbia",
      "stateAbbreviation": "DC",
      "totalEmployment": 310,
      "medianAnnual": 124930,
      "meanAnnual": 120840,
      "pct10Annual": 89820,
      "pct90Annual": 156280,
      "locationQuotient": 1.06
    },
    {
      "state": "Florida",
      "stateSlug": "florida",
      "stateAbbreviation": "FL",
      "totalEmployment": 1840,
      "medianAnnual": 76490,
      "meanAnnual": 82280,
      "pct10Annual": 46480,
      "pct90Annual": 128940,
      "locationQuotient": 0.45
    },
    {
      "state": "Georgia",
      "stateSlug": "georgia",
      "stateAbbreviation": "GA",
      "totalEmployment": 950,
      "medianAnnual": 75910,
      "meanAnnual": 77670,
      "pct10Annual": 18600,
      "pct90Annual": 135810,
      "locationQuotient": 0.47
    },
    {
      "state": "Hawaii",
      "stateSlug": "hawaii",
      "stateAbbreviation": "HI",
      "totalEmployment": 500,
      "medianAnnual": 102070,
      "meanAnnual": 107110,
      "pct10Annual": 63130,
      "pct90Annual": 163850,
      "locationQuotient": 1.93
    },
    {
      "state": "Idaho",
      "stateSlug": "idaho",
      "stateAbbreviation": "ID",
      "totalEmployment": 130,
      "medianAnnual": 84100,
      "meanAnnual": 85410,
      "pct10Annual": 49220,
      "pct90Annual": 124790,
      "locationQuotient": 0.37
    },
    {
      "state": "Illinois",
      "stateSlug": "illinois",
      "stateAbbreviation": "IL",
      "totalEmployment": 3720,
      "medianAnnual": 95080,
      "meanAnnual": 99730,
      "pct10Annual": 60800,
      "pct90Annual": 143450,
      "locationQuotient": 1.46
    },
    {
      "state": "Indiana",
      "stateSlug": "indiana",
      "stateAbbreviation": "IN",
      "totalEmployment": 2630,
      "medianAnnual": 81820,
      "meanAnnual": 84250,
      "pct10Annual": 38290,
      "pct90Annual": 121000,
      "locationQuotient": 1.97
    },
    {
      "state": "Iowa",
      "stateSlug": "iowa",
      "stateAbbreviation": "IA",
      "totalEmployment": 590,
      "medianAnnual": 78260,
      "meanAnnual": 82540,
      "pct10Annual": 50710,
      "pct90Annual": 131230,
      "locationQuotient": 0.89
    },
    {
      "state": "Kansas",
      "stateSlug": "kansas",
      "stateAbbreviation": "KS",
      "totalEmployment": 390,
      "medianAnnual": 73020,
      "meanAnnual": 72460,
      "pct10Annual": 15080,
      "pct90Annual": 123910,
      "locationQuotient": 0.64
    },
    {
      "state": "Kentucky",
      "stateSlug": "kentucky",
      "stateAbbreviation": "KY",
      "totalEmployment": 780,
      "medianAnnual": 61800,
      "meanAnnual": 58420,
      "pct10Annual": 15490,
      "pct90Annual": 92130,
      "locationQuotient": 0.93
    },
    {
      "state": "Louisiana",
      "stateSlug": "louisiana",
      "stateAbbreviation": "LA",
      "totalEmployment": 130,
      "medianAnnual": 75280,
      "meanAnnual": 73050,
      "pct10Annual": 47080,
      "pct90Annual": 93130,
      "locationQuotient": 0.16
    },
    {
      "state": "Maine",
      "stateSlug": "maine",
      "stateAbbreviation": "ME",
      "totalEmployment": 230,
      "medianAnnual": 95740,
      "meanAnnual": 98270,
      "pct10Annual": 58750,
      "pct90Annual": 134930,
      "locationQuotient": 0.88
    },
    {
      "state": "Maryland",
      "stateSlug": "maryland",
      "stateAbbreviation": "MD",
      "totalEmployment": 870,
      "medianAnnual": 95450,
      "meanAnnual": 96560,
      "pct10Annual": 66200,
      "pct90Annual": 131310,
      "locationQuotient": 0.75
    },
    {
      "state": "Massachusetts",
      "stateSlug": "massachusetts",
      "stateAbbreviation": "MA",
      "totalEmployment": 1680,
      "medianAnnual": 97490,
      "meanAnnual": 102640,
      "pct10Annual": 50670,
      "pct90Annual": 153520,
      "locationQuotient": 1.1
    },
    {
      "state": "Michigan",
      "stateSlug": "michigan",
      "stateAbbreviation": "MI",
      "totalEmployment": 2420,
      "medianAnnual": 78600,
      "meanAnnual": 76540,
      "pct10Annual": 21490,
      "pct90Annual": 106550,
      "locationQuotient": 1.31
    },
    {
      "state": "Minnesota",
      "stateSlug": "minnesota",
      "stateAbbreviation": "MN",
      "totalEmployment": 1660,
      "medianAnnual": 95640,
      "meanAnnual": 97940,
      "pct10Annual": 76950,
      "pct90Annual": 124040,
      "locationQuotient": 1.35
    },
    {
      "state": "Mississippi",
      "stateSlug": "mississippi",
      "stateAbbreviation": "MS",
      "totalEmployment": 180,
      "medianAnnual": 71550,
      "meanAnnual": 70400,
      "pct10Annual": 33850,
      "pct90Annual": 102040,
      "locationQuotient": 0.38
    },
    {
      "state": "Missouri",
      "stateSlug": "missouri",
      "stateAbbreviation": "MO",
      "totalEmployment": 1050,
      "medianAnnual": 93910,
      "meanAnnual": 91710,
      "pct10Annual": 47570,
      "pct90Annual": 136450,
      "locationQuotient": 0.86
    },
    {
      "state": "Montana",
      "stateSlug": "montana",
      "stateAbbreviation": "MT",
      "totalEmployment": 150,
      "medianAnnual": 64360,
      "meanAnnual": 80820,
      "pct10Annual": 36710,
      "pct90Annual": 157100,
      "locationQuotient": 0.7
    },
    {
      "state": "Nebraska",
      "stateSlug": "nebraska",
      "stateAbbreviation": "NE",
      "totalEmployment": 320,
      "medianAnnual": 81360,
      "meanAnnual": 83390,
      "pct10Annual": 35850,
      "pct90Annual": 122430,
      "locationQuotient": 0.75
    },
    {
      "state": "Nevada",
      "stateSlug": "nevada",
      "stateAbbreviation": "NV",
      "totalEmployment": 540,
      "medianAnnual": 75730,
      "meanAnnual": 96860,
      "pct10Annual": 62680,
      "pct90Annual": 148880,
      "locationQuotient": 0.84
    },
    {
      "state": "New Hampshire",
      "stateSlug": "new-hampshire",
      "stateAbbreviation": "NH",
      "totalEmployment": 180,
      "medianAnnual": 106070,
      "meanAnnual": 105600,
      "pct10Annual": 28410,
      "pct90Annual": 163790,
      "locationQuotient": 0.63
    },
    {
      "state": "New Jersey",
      "stateSlug": "new-jersey",
      "stateAbbreviation": "NJ",
      "totalEmployment": 2920,
      "medianAnnual": 118940,
      "meanAnnual": 115720,
      "pct10Annual": 65010,
      "pct90Annual": 163580,
      "locationQuotient": 1.64
    },
    {
      "state": "New Mexico",
      "stateSlug": "new-mexico",
      "stateAbbreviation": "NM",
      "totalEmployment": 230,
      "medianAnnual": 100420,
      "meanAnnual": 90470,
      "pct10Annual": 56490,
      "pct90Annual": 127720,
      "locationQuotient": 0.62
    },
    {
      "state": "New York",
      "stateSlug": "new-york",
      "stateAbbreviation": "NY",
      "totalEmployment": 6990,
      "medianAnnual": 98200,
      "meanAnnual": 109900,
      "pct10Annual": 58610,
      "pct90Annual": 173680,
      "locationQuotient": 1.75
    },
    {
      "state": "North Carolina",
      "stateSlug": "north-carolina",
      "stateAbbreviation": "NC",
      "totalEmployment": 850,
      "medianAnnual": 88270,
      "meanAnnual": 89820,
      "pct10Annual": 59870,
      "pct90Annual": 120640,
      "locationQuotient": 0.41
    },
    {
      "state": "North Dakota",
      "stateSlug": "north-dakota",
      "stateAbbreviation": "ND",
      "totalEmployment": 80,
      "medianAnnual": 105590,
      "meanAnnual": 95700,
      "pct10Annual": 64730,
      "pct90Annual": 139200,
      "locationQuotient": 0.44
    },
    {
      "state": "Ohio",
      "stateSlug": "ohio",
      "stateAbbreviation": "OH",
      "totalEmployment": 4080,
      "medianAnnual": 76810,
      "meanAnnual": 85660,
      "pct10Annual": 51830,
      "pct90Annual": 128590,
      "locationQuotient": 1.76
    },
    {
      "state": "Oklahoma",
      "stateSlug": "oklahoma",
      "stateAbbreviation": "OK",
      "totalEmployment": 300,
      "medianAnnual": 82080,
      "meanAnnual": 82570,
      "pct10Annual": 45360,
      "pct90Annual": 112050,
      "locationQuotient": 0.43
    },
    {
      "state": "Oregon",
      "stateSlug": "oregon",
      "stateAbbreviation": "OR",
      "totalEmployment": 1010,
      "medianAnnual": 103210,
      "meanAnnual": 103110,
      "pct10Annual": 56470,
      "pct90Annual": 135800,
      "locationQuotient": 1.22
    },
    {
      "state": "Pennsylvania",
      "stateSlug": "pennsylvania",
      "stateAbbreviation": "PA",
      "totalEmployment": 3500,
      "medianAnnual": 79330,
      "meanAnnual": 89340,
      "pct10Annual": 51640,
      "pct90Annual": 141010,
      "locationQuotient": 1.39
    },
    {
      "state": "Rhode Island",
      "stateSlug": "rhode-island",
      "stateAbbreviation": "RI",
      "totalEmployment": 450,
      "medianAnnual": 72360,
      "meanAnnual": 93810,
      "pct10Annual": 55050,
      "pct90Annual": 136420,
      "locationQuotient": 2.19
    },
    {
      "state": "South Carolina",
      "stateSlug": "south-carolina",
      "stateAbbreviation": "SC",
      "totalEmployment": 450,
      "medianAnnual": 62370,
      "meanAnnual": 73270,
      "pct10Annual": 16340,
      "pct90Annual": 159400,
      "locationQuotient": 0.47
    },
    {
      "state": "South Dakota",
      "stateSlug": "south-dakota",
      "stateAbbreviation": "SD",
      "totalEmployment": 90,
      "medianAnnual": 78180,
      "meanAnnual": 92940,
      "pct10Annual": 50620,
      "pct90Annual": 157590,
      "locationQuotient": 0.48
    },
    {
      "state": "Tennessee",
      "stateSlug": "tennessee",
      "stateAbbreviation": "TN",
      "totalEmployment": 730,
      "medianAnnual": 66640,
      "meanAnnual": 75460,
      "pct10Annual": 28790,
      "pct90Annual": 131330,
      "locationQuotient": 0.53
    },
    {
      "state": "Texas",
      "stateSlug": "texas",
      "stateAbbreviation": "TX",
      "totalEmployment": 2570,
      "medianAnnual": 77750,
      "meanAnnual": 83050,
      "pct10Annual": 45970,
      "pct90Annual": 133600,
      "locationQuotient": 0.44
    },
    {
      "state": "Utah",
      "stateSlug": "utah",
      "stateAbbreviation": "UT",
      "totalEmployment": 210,
      "medianAnnual": 91730,
      "meanAnnual": 93240,
      "pct10Annual": 31140,
      "pct90Annual": 124800,
      "locationQuotient": 0.3
    },
    {
      "state": "Vermont",
      "stateSlug": "vermont",
      "stateAbbreviation": "VT",
      "totalEmployment": 150,
      "medianAnnual": 83420,
      "meanAnnual": 92230,
      "pct10Annual": 61680,
      "pct90Annual": 137090,
      "locationQuotient": 1.15
    },
    {
      "state": "Virginia",
      "stateSlug": "virginia",
      "stateAbbreviation": "VA",
      "totalEmployment": 1080,
      "medianAnnual": 92410,
      "meanAnnual": 96500,
      "pct10Annual": 58430,
      "pct90Annual": 153770,
      "locationQuotient": 0.63
    },
    {
      "state": "Washington",
      "stateSlug": "washington",
      "stateAbbreviation": "WA",
      "totalEmployment": 2780,
      "medianAnnual": 108110,
      "meanAnnual": 112910,
      "pct10Annual": 58930,
      "pct90Annual": 170920,
      "locationQuotient": 1.88
    },
    {
      "state": "West Virginia",
      "stateSlug": "west-virginia",
      "stateAbbreviation": "WV",
      "totalEmployment": 430,
      "medianAnnual": 96410,
      "meanAnnual": 94330,
      "pct10Annual": 64850,
      "pct90Annual": 122270,
      "locationQuotient": 1.46
    },
    {
      "state": "Wisconsin",
      "stateSlug": "wisconsin",
      "stateAbbreviation": "WI",
      "totalEmployment": 2010,
      "medianAnnual": 85620,
      "meanAnnual": 88080,
      "pct10Annual": 18870,
      "pct90Annual": 138290,
      "locationQuotient": 1.64
    },
    {
      "state": "Wyoming",
      "stateSlug": "wyoming",
      "stateAbbreviation": "WY",
      "totalEmployment": 90,
      "medianAnnual": 97620,
      "meanAnnual": 91290,
      "pct10Annual": 62540,
      "pct90Annual": 119040,
      "locationQuotient": 0.78
    }
  ]
}