{
  "title": "Legal Secretaries and Administrative Assistants",
  "slug": "legal-secretaries-and-administrative-assistants",
  "socCode": "43-6012",
  "dataYear": 2024,
  "typicalEducation": null,
  "workExperience": null,
  "onJobTraining": null,
  "jobOutlookPercent": null,
  "jobOutlookLabel": null,
  "national": {
    "totalEmployment": 154540,
    "meanHourly": 29,
    "meanAnnual": 60320,
    "medianHourly": 26.03,
    "medianAnnual": 54140,
    "pct10Hourly": 17.08,
    "pct25Hourly": 20.54,
    "pct75Hourly": 34.66,
    "pct90Hourly": 42.15,
    "pct10Annual": 35530,
    "pct25Annual": 42720,
    "pct75Annual": 72090,
    "pct90Annual": 87660
  },
  "states": [
    {
      "state": "Alabama",
      "stateSlug": "alabama",
      "stateAbbreviation": "AL",
      "totalEmployment": 1920,
      "medianAnnual": 46390,
      "meanAnnual": 43620,
      "pct10Annual": 27230,
      "pct90Annual": 58390,
      "locationQuotient": 0.92
    },
    {
      "state": "Alaska",
      "stateSlug": "alaska",
      "stateAbbreviation": "AK",
      "totalEmployment": 560,
      "medianAnnual": 59600,
      "meanAnnual": 60840,
      "pct10Annual": 45120,
      "pct90Annual": 84660,
      "locationQuotient": 1.74
    },
    {
      "state": "Arizona",
      "stateSlug": "arizona",
      "stateAbbreviation": "AZ",
      "totalEmployment": 3320,
      "medianAnnual": 47990,
      "meanAnnual": 52000,
      "pct10Annual": 36280,
      "pct90Annual": 79310,
      "locationQuotient": 1.04
    },
    {
      "state": "Arkansas",
      "stateSlug": "arkansas",
      "stateAbbreviation": "AR",
      "totalEmployment": 930,
      "medianAnnual": 39400,
      "meanAnnual": 40120,
      "pct10Annual": 29520,
      "pct90Annual": 48450,
      "locationQuotient": 0.72
    },
    {
      "state": "California",
      "stateSlug": "california",
      "stateAbbreviation": "CA",
      "totalEmployment": 23960,
      "medianAnnual": 61320,
      "meanAnnual": 78700,
      "pct10Annual": 41530,
      "pct90Annual": 106130,
      "locationQuotient": 1.32
    },
    {
      "state": "Colorado",
      "stateSlug": "colorado",
      "stateAbbreviation": "CO",
      "totalEmployment": 1910,
      "medianAnnual": 56560,
      "meanAnnual": 63730,
      "pct10Annual": 43900,
      "pct90Annual": 95960,
      "locationQuotient": 0.66
    },
    {
      "state": "Connecticut",
      "stateSlug": "connecticut",
      "stateAbbreviation": "CT",
      "totalEmployment": 1140,
      "medianAnnual": 61440,
      "meanAnnual": 67520,
      "pct10Annual": 47880,
      "pct90Annual": 96020,
      "locationQuotient": 0.67
    },
    {
      "state": "Delaware",
      "stateSlug": "delaware",
      "stateAbbreviation": "DE",
      "totalEmployment": 970,
      "medianAnnual": 63740,
      "meanAnnual": 62690,
      "pct10Annual": 37090,
      "pct90Annual": 83100,
      "locationQuotient": 2.04
    },
    {
      "state": "District of Columbia",
      "stateSlug": "district-of-columbia",
      "stateAbbreviation": "DC",
      "totalEmployment": 2040,
      "medianAnnual": 101170,
      "meanAnnual": 95280,
      "pct10Annual": 56320,
      "pct90Annual": 122370,
      "locationQuotient": 2.86
    },
    {
      "state": "Florida",
      "stateSlug": "florida",
      "stateAbbreviation": "FL",
      "totalEmployment": 10970,
      "medianAnnual": 53790,
      "meanAnnual": 58090,
      "pct10Annual": 30640,
      "pct90Annual": 81940,
      "locationQuotient": 1.11
    },
    {
      "state": "Georgia",
      "stateSlug": "georgia",
      "stateAbbreviation": "GA",
      "totalEmployment": 1990,
      "medianAnnual": 51000,
      "meanAnnual": 55760,
      "pct10Annual": 32220,
      "pct90Annual": 83010,
      "locationQuotient": 0.41
    },
    {
      "state": "Hawaii",
      "stateSlug": "hawaii",
      "stateAbbreviation": "HI",
      "totalEmployment": 520,
      "medianAnnual": 57030,
      "meanAnnual": 59030,
      "pct10Annual": 46020,
      "pct90Annual": 77190,
      "locationQuotient": 0.83
    },
    {
      "state": "Idaho",
      "stateSlug": "idaho",
      "stateAbbreviation": "ID",
      "totalEmployment": 550,
      "medianAnnual": 41920,
      "meanAnnual": 45360,
      "pct10Annual": 30050,
      "pct90Annual": 60960,
      "locationQuotient": 0.65
    },
    {
      "state": "Illinois",
      "stateSlug": "illinois",
      "stateAbbreviation": "IL",
      "totalEmployment": 8860,
      "medianAnnual": 58070,
      "meanAnnual": 60730,
      "pct10Annual": 39140,
      "pct90Annual": 100370,
      "locationQuotient": 1.46
    },
    {
      "state": "Indiana",
      "stateSlug": "indiana",
      "stateAbbreviation": "IN",
      "totalEmployment": 2400,
      "medianAnnual": 47260,
      "meanAnnual": 50020,
      "pct10Annual": 30520,
      "pct90Annual": 74710,
      "locationQuotient": 0.75
    },
    {
      "state": "Iowa",
      "stateSlug": "iowa",
      "stateAbbreviation": "IA",
      "totalEmployment": 1190,
      "medianAnnual": null,
      "meanAnnual": null,
      "pct10Annual": null,
      "pct90Annual": null,
      "locationQuotient": 0.76
    },
    {
      "state": "Kansas",
      "stateSlug": "kansas",
      "stateAbbreviation": "KS",
      "totalEmployment": 830,
      "medianAnnual": 41640,
      "meanAnnual": 43100,
      "pct10Annual": 30340,
      "pct90Annual": 55350,
      "locationQuotient": 0.58
    },
    {
      "state": "Kentucky",
      "stateSlug": "kentucky",
      "stateAbbreviation": "KY",
      "totalEmployment": 2190,
      "medianAnnual": 38330,
      "meanAnnual": 43040,
      "pct10Annual": 25390,
      "pct90Annual": 63690,
      "locationQuotient": 1.1
    },
    {
      "state": "Louisiana",
      "stateSlug": "louisiana",
      "stateAbbreviation": "LA",
      "totalEmployment": 2790,
      "medianAnnual": 42560,
      "meanAnnual": 46890,
      "pct10Annual": 30670,
      "pct90Annual": 71830,
      "locationQuotient": 1.46
    },
    {
      "state": "Maine",
      "stateSlug": "maine",
      "stateAbbreviation": "ME",
      "totalEmployment": 610,
      "medianAnnual": 49950,
      "meanAnnual": 51190,
      "pct10Annual": 37440,
      "pct90Annual": 62490,
      "locationQuotient": 0.95
    },
    {
      "state": "Maryland",
      "stateSlug": "maryland",
      "stateAbbreviation": "MD",
      "totalEmployment": 1410,
      "medianAnnual": 63110,
      "meanAnnual": 65950,
      "pct10Annual": 45140,
      "pct90Annual": 82580,
      "locationQuotient": 0.51
    },
    {
      "state": "Massachusetts",
      "stateSlug": "massachusetts",
      "stateAbbreviation": "MA",
      "totalEmployment": 3880,
      "medianAnnual": 61440,
      "meanAnnual": 65780,
      "pct10Annual": 38780,
      "pct90Annual": 95720,
      "locationQuotient": 1.06
    },
    {
      "state": "Michigan",
      "stateSlug": "michigan",
      "stateAbbreviation": "MI",
      "totalEmployment": 3070,
      "medianAnnual": 56030,
      "meanAnnual": 57200,
      "pct10Annual": 34520,
      "pct90Annual": 80950,
      "locationQuotient": 0.7
    },
    {
      "state": "Minnesota",
      "stateSlug": "minnesota",
      "stateAbbreviation": "MN",
      "totalEmployment": 2500,
      "medianAnnual": 61300,
      "meanAnnual": 65160,
      "pct10Annual": 47420,
      "pct90Annual": 84040,
      "locationQuotient": 0.85
    },
    {
      "state": "Mississippi",
      "stateSlug": "mississippi",
      "stateAbbreviation": "MS",
      "totalEmployment": 790,
      "medianAnnual": 43830,
      "meanAnnual": 43720,
      "pct10Annual": 27180,
      "pct90Annual": 66580,
      "locationQuotient": 0.68
    },
    {
      "state": "Missouri",
      "stateSlug": "missouri",
      "stateAbbreviation": "MO",
      "totalEmployment": 2320,
      "medianAnnual": 47650,
      "meanAnnual": 50880,
      "pct10Annual": 35070,
      "pct90Annual": 77050,
      "locationQuotient": 0.79
    },
    {
      "state": "Montana",
      "stateSlug": "montana",
      "stateAbbreviation": "MT",
      "totalEmployment": 630,
      "medianAnnual": 43230,
      "meanAnnual": 45570,
      "pct10Annual": 33680,
      "pct90Annual": 57660,
      "locationQuotient": 1.22
    },
    {
      "state": "Nebraska",
      "stateSlug": "nebraska",
      "stateAbbreviation": "NE",
      "totalEmployment": 1210,
      "medianAnnual": 47770,
      "meanAnnual": 48500,
      "pct10Annual": 30010,
      "pct90Annual": 64290,
      "locationQuotient": 1.19
    },
    {
      "state": "Nevada",
      "stateSlug": "nevada",
      "stateAbbreviation": "NV",
      "totalEmployment": 1450,
      "medianAnnual": 51540,
      "meanAnnual": 57820,
      "pct10Annual": 36120,
      "pct90Annual": 78470,
      "locationQuotient": 0.95
    },
    {
      "state": "New Hampshire",
      "stateSlug": "new-hampshire",
      "stateAbbreviation": "NH",
      "totalEmployment": 490,
      "medianAnnual": 49880,
      "meanAnnual": 55450,
      "pct10Annual": 33830,
      "pct90Annual": 81410,
      "locationQuotient": 0.72
    },
    {
      "state": "New Jersey",
      "stateSlug": "new-jersey",
      "stateAbbreviation": "NJ",
      "totalEmployment": 3910,
      "medianAnnual": 60400,
      "meanAnnual": 62510,
      "pct10Annual": 43830,
      "pct90Annual": 83990,
      "locationQuotient": 0.92
    },
    {
      "state": "New Mexico",
      "stateSlug": "new-mexico",
      "stateAbbreviation": "NM",
      "totalEmployment": 1330,
      "medianAnnual": 47900,
      "meanAnnual": 50460,
      "pct10Annual": 38020,
      "pct90Annual": 66350,
      "locationQuotient": 1.55
    },
    {
      "state": "New York",
      "stateSlug": "new-york",
      "stateAbbreviation": "NY",
      "totalEmployment": 15430,
      "medianAnnual": 74400,
      "meanAnnual": 71310,
      "pct10Annual": 38650,
      "pct90Annual": 103380,
      "locationQuotient": 1.61
    },
    {
      "state": "North Carolina",
      "stateSlug": "north-carolina",
      "stateAbbreviation": "NC",
      "totalEmployment": 4460,
      "medianAnnual": 43830,
      "meanAnnual": 46450,
      "pct10Annual": 29410,
      "pct90Annual": 69100,
      "locationQuotient": 0.91
    },
    {
      "state": "North Dakota",
      "stateSlug": "north-dakota",
      "stateAbbreviation": "ND",
      "totalEmployment": 320,
      "medianAnnual": 53460,
      "meanAnnual": 52150,
      "pct10Annual": 36120,
      "pct90Annual": 65210,
      "locationQuotient": 0.75
    },
    {
      "state": "Ohio",
      "stateSlug": "ohio",
      "stateAbbreviation": "OH",
      "totalEmployment": 5170,
      "medianAnnual": 46710,
      "meanAnnual": 49340,
      "pct10Annual": 31200,
      "pct90Annual": 72990,
      "locationQuotient": 0.93
    },
    {
      "state": "Oklahoma",
      "stateSlug": "oklahoma",
      "stateAbbreviation": "OK",
      "totalEmployment": 1430,
      "medianAnnual": 47440,
      "meanAnnual": 46370,
      "pct10Annual": 31880,
      "pct90Annual": 59310,
      "locationQuotient": 0.84
    },
    {
      "state": "Oregon",
      "stateSlug": "oregon",
      "stateAbbreviation": "OR",
      "totalEmployment": 900,
      "medianAnnual": 55590,
      "meanAnnual": 58240,
      "pct10Annual": 43740,
      "pct90Annual": 80690,
      "locationQuotient": 0.45
    },
    {
      "state": "Pennsylvania",
      "stateSlug": "pennsylvania",
      "stateAbbreviation": "PA",
      "totalEmployment": 6440,
      "medianAnnual": 49330,
      "meanAnnual": 52570,
      "pct10Annual": 34620,
      "pct90Annual": 74750,
      "locationQuotient": 1.07
    },
    {
      "state": "Rhode Island",
      "stateSlug": "rhode-island",
      "stateAbbreviation": "RI",
      "totalEmployment": null,
      "medianAnnual": 61970,
      "meanAnnual": 59120,
      "pct10Annual": 39380,
      "pct90Annual": 82720,
      "locationQuotient": null
    },
    {
      "state": "South Carolina",
      "stateSlug": "south-carolina",
      "stateAbbreviation": "SC",
      "totalEmployment": 2120,
      "medianAnnual": 39670,
      "meanAnnual": 42420,
      "pct10Annual": 27830,
      "pct90Annual": 55450,
      "locationQuotient": 0.93
    },
    {
      "state": "South Dakota",
      "stateSlug": "south-dakota",
      "stateAbbreviation": "SD",
      "totalEmployment": 660,
      "medianAnnual": 46020,
      "meanAnnual": 44850,
      "pct10Annual": 35620,
      "pct90Annual": 58670,
      "locationQuotient": 1.46
    },
    {
      "state": "Tennessee",
      "stateSlug": "tennessee",
      "stateAbbreviation": "TN",
      "totalEmployment": 3440,
      "medianAnnual": 44280,
      "meanAnnual": 44630,
      "pct10Annual": 29890,
      "pct90Annual": 61210,
      "locationQuotient": 1.05
    },
    {
      "state": "Texas",
      "stateSlug": "texas",
      "stateAbbreviation": "TX",
      "totalEmployment": 9900,
      "medianAnnual": 49150,
      "meanAnnual": 54370,
      "pct10Annual": 35290,
      "pct90Annual": 80740,
      "locationQuotient": 0.71
    },
    {
      "state": "Utah",
      "stateSlug": "utah",
      "stateAbbreviation": "UT",
      "totalEmployment": 1060,
      "medianAnnual": 46050,
      "meanAnnual": 48780,
      "pct10Annual": 35410,
      "pct90Annual": 69390,
      "locationQuotient": 0.62
    },
    {
      "state": "Vermont",
      "stateSlug": "vermont",
      "stateAbbreviation": "VT",
      "totalEmployment": 290,
      "medianAnnual": 47050,
      "meanAnnual": 47440,
      "pct10Annual": 36820,
      "pct90Annual": 57880,
      "locationQuotient": 0.95
    },
    {
      "state": "Virginia",
      "stateSlug": "virginia",
      "stateAbbreviation": "VA",
      "totalEmployment": 2800,
      "medianAnnual": 51010,
      "meanAnnual": 56390,
      "pct10Annual": 30090,
      "pct90Annual": 75660,
      "locationQuotient": 0.69
    },
    {
      "state": "Washington",
      "stateSlug": "washington",
      "stateAbbreviation": "WA",
      "totalEmployment": 4090,
      "medianAnnual": 59680,
      "meanAnnual": 61190,
      "pct10Annual": 42470,
      "pct90Annual": 81990,
      "locationQuotient": 1.15
    },
    {
      "state": "West Virginia",
      "stateSlug": "west-virginia",
      "stateAbbreviation": "WV",
      "totalEmployment": 1280,
      "medianAnnual": 46940,
      "meanAnnual": 46340,
      "pct10Annual": 30710,
      "pct90Annual": 58720,
      "locationQuotient": 1.82
    },
    {
      "state": "Wisconsin",
      "stateSlug": "wisconsin",
      "stateAbbreviation": "WI",
      "totalEmployment": 1160,
      "medianAnnual": 48980,
      "meanAnnual": 53350,
      "pct10Annual": 40300,
      "pct90Annual": 73660,
      "locationQuotient": 0.39
    },
    {
      "state": "Wyoming",
      "stateSlug": "wyoming",
      "stateAbbreviation": "WY",
      "totalEmployment": 210,
      "medianAnnual": 42590,
      "meanAnnual": 46660,
      "pct10Annual": 39020,
      "pct90Annual": 61370,
      "locationQuotient": 0.76
    }
  ]
}