{
  "title": "Orderlies",
  "slug": "orderlies",
  "socCode": "31-1132",
  "dataYear": 2024,
  "typicalEducation": null,
  "workExperience": null,
  "onJobTraining": null,
  "jobOutlookPercent": null,
  "jobOutlookLabel": null,
  "national": {
    "totalEmployment": 53020,
    "meanHourly": 19.27,
    "meanAnnual": 40070,
    "medianHourly": 18.12,
    "medianAnnual": 37700,
    "pct10Hourly": 15.2,
    "pct25Hourly": 16.76,
    "pct75Hourly": 20.75,
    "pct90Hourly": 23.83,
    "pct10Annual": 31610,
    "pct25Annual": 34850,
    "pct75Annual": 43160,
    "pct90Annual": 49570
  },
  "states": [
    {
      "state": "Alabama",
      "stateSlug": "alabama",
      "stateAbbreviation": "AL",
      "totalEmployment": 490,
      "medianAnnual": 31240,
      "meanAnnual": 31670,
      "pct10Annual": 24770,
      "pct90Annual": 40670,
      "locationQuotient": 0.68
    },
    {
      "state": "Alaska",
      "stateSlug": "alaska",
      "stateAbbreviation": "AK",
      "totalEmployment": 80,
      "medianAnnual": 40610,
      "meanAnnual": 43480,
      "pct10Annual": 38700,
      "pct90Annual": 47240,
      "locationQuotient": 0.69
    },
    {
      "state": "Arizona",
      "stateSlug": "arizona",
      "stateAbbreviation": "AZ",
      "totalEmployment": 940,
      "medianAnnual": 36910,
      "meanAnnual": 37810,
      "pct10Annual": 34800,
      "pct90Annual": 43310,
      "locationQuotient": 0.86
    },
    {
      "state": "Arkansas",
      "stateSlug": "arkansas",
      "stateAbbreviation": "AR",
      "totalEmployment": 270,
      "medianAnnual": 31120,
      "meanAnnual": 31010,
      "pct10Annual": 23490,
      "pct90Annual": 36260,
      "locationQuotient": 0.6
    },
    {
      "state": "California",
      "stateSlug": "california",
      "stateAbbreviation": "CA",
      "totalEmployment": 5140,
      "medianAnnual": 48550,
      "meanAnnual": 53950,
      "pct10Annual": 37930,
      "pct90Annual": 74950,
      "locationQuotient": 0.83
    },
    {
      "state": "Colorado",
      "stateSlug": "colorado",
      "stateAbbreviation": "CO",
      "totalEmployment": 680,
      "medianAnnual": 41390,
      "meanAnnual": 41540,
      "pct10Annual": 37060,
      "pct90Annual": 46670,
      "locationQuotient": 0.68
    },
    {
      "state": "Connecticut",
      "stateSlug": "connecticut",
      "stateAbbreviation": "CT",
      "totalEmployment": 990,
      "medianAnnual": 35840,
      "meanAnnual": 37510,
      "pct10Annual": 34000,
      "pct90Annual": 45360,
      "locationQuotient": 1.7
    },
    {
      "state": "Delaware",
      "stateSlug": "delaware",
      "stateAbbreviation": "DE",
      "totalEmployment": 200,
      "medianAnnual": 42440,
      "meanAnnual": 40910,
      "pct10Annual": 35100,
      "pct90Annual": 42440,
      "locationQuotient": 1.23
    },
    {
      "state": "District of Columbia",
      "stateSlug": "district-of-columbia",
      "stateAbbreviation": "DC",
      "totalEmployment": 80,
      "medianAnnual": 37450,
      "meanAnnual": 38310,
      "pct10Annual": 36500,
      "pct90Annual": 38790,
      "locationQuotient": 0.31
    },
    {
      "state": "Florida",
      "stateSlug": "florida",
      "stateAbbreviation": "FL",
      "totalEmployment": 3850,
      "medianAnnual": 34560,
      "meanAnnual": 35230,
      "pct10Annual": 31380,
      "pct90Annual": 38630,
      "locationQuotient": 1.14
    },
    {
      "state": "Georgia",
      "stateSlug": "georgia",
      "stateAbbreviation": "GA",
      "totalEmployment": 2570,
      "medianAnnual": 34780,
      "meanAnnual": 34890,
      "pct10Annual": 28270,
      "pct90Annual": 42520,
      "locationQuotient": 1.54
    },
    {
      "state": "Hawaii",
      "stateSlug": "hawaii",
      "stateAbbreviation": "HI",
      "totalEmployment": 90,
      "medianAnnual": 45740,
      "meanAnnual": 43120,
      "pct10Annual": 39920,
      "pct90Annual": 45930,
      "locationQuotient": 0.43
    },
    {
      "state": "Idaho",
      "stateSlug": "idaho",
      "stateAbbreviation": "ID",
      "totalEmployment": 210,
      "medianAnnual": 38090,
      "meanAnnual": 40080,
      "pct10Annual": 34020,
      "pct90Annual": 47590,
      "locationQuotient": 0.71
    },
    {
      "state": "Illinois",
      "stateSlug": "illinois",
      "stateAbbreviation": "IL",
      "totalEmployment": 2160,
      "medianAnnual": 38480,
      "meanAnnual": 39270,
      "pct10Annual": 33850,
      "pct90Annual": 45440,
      "locationQuotient": 1.03
    },
    {
      "state": "Indiana",
      "stateSlug": "indiana",
      "stateAbbreviation": "IN",
      "totalEmployment": 1420,
      "medianAnnual": 38820,
      "meanAnnual": 37870,
      "pct10Annual": 33540,
      "pct90Annual": 40280,
      "locationQuotient": 1.3
    },
    {
      "state": "Iowa",
      "stateSlug": "iowa",
      "stateAbbreviation": "IA",
      "totalEmployment": 270,
      "medianAnnual": 36210,
      "meanAnnual": 36540,
      "pct10Annual": 32620,
      "pct90Annual": 41150,
      "locationQuotient": 0.5
    },
    {
      "state": "Kansas",
      "stateSlug": "kansas",
      "stateAbbreviation": "KS",
      "totalEmployment": 190,
      "medianAnnual": 36440,
      "meanAnnual": 37790,
      "pct10Annual": 31480,
      "pct90Annual": 42640,
      "locationQuotient": 0.38
    },
    {
      "state": "Kentucky",
      "stateSlug": "kentucky",
      "stateAbbreviation": "KY",
      "totalEmployment": 720,
      "medianAnnual": 36400,
      "meanAnnual": 34770,
      "pct10Annual": 29260,
      "pct90Annual": 38270,
      "locationQuotient": 1.05
    },
    {
      "state": "Louisiana",
      "stateSlug": "louisiana",
      "stateAbbreviation": "LA",
      "totalEmployment": 430,
      "medianAnnual": 26350,
      "meanAnnual": 27450,
      "pct10Annual": 19620,
      "pct90Annual": 33750,
      "locationQuotient": 0.66
    },
    {
      "state": "Maine",
      "stateSlug": "maine",
      "stateAbbreviation": "ME",
      "totalEmployment": 100,
      "medianAnnual": 37970,
      "meanAnnual": 41650,
      "pct10Annual": 35730,
      "pct90Annual": 47490,
      "locationQuotient": 0.46
    },
    {
      "state": "Maryland",
      "stateSlug": "maryland",
      "stateAbbreviation": "MD",
      "totalEmployment": 1500,
      "medianAnnual": 37020,
      "meanAnnual": 36830,
      "pct10Annual": 31610,
      "pct90Annual": 40920,
      "locationQuotient": 1.59
    },
    {
      "state": "Massachusetts",
      "stateSlug": "massachusetts",
      "stateAbbreviation": "MA",
      "totalEmployment": 1510,
      "medianAnnual": 39420,
      "meanAnnual": 41970,
      "pct10Annual": 35990,
      "pct90Annual": 49400,
      "locationQuotient": 1.21
    },
    {
      "state": "Michigan",
      "stateSlug": "michigan",
      "stateAbbreviation": "MI",
      "totalEmployment": 1560,
      "medianAnnual": 35810,
      "meanAnnual": 36240,
      "pct10Annual": 31570,
      "pct90Annual": 40400,
      "locationQuotient": 1.03
    },
    {
      "state": "Minnesota",
      "stateSlug": "minnesota",
      "stateAbbreviation": "MN",
      "totalEmployment": 370,
      "medianAnnual": 44970,
      "meanAnnual": 44430,
      "pct10Annual": 36930,
      "pct90Annual": 52520,
      "locationQuotient": 0.37
    },
    {
      "state": "Mississippi",
      "stateSlug": "mississippi",
      "stateAbbreviation": "MS",
      "totalEmployment": 360,
      "medianAnnual": 30070,
      "meanAnnual": 29940,
      "pct10Annual": 24060,
      "pct90Annual": 36440,
      "locationQuotient": 0.89
    },
    {
      "state": "Missouri",
      "stateSlug": "missouri",
      "stateAbbreviation": "MO",
      "totalEmployment": 860,
      "medianAnnual": 36190,
      "meanAnnual": 37380,
      "pct10Annual": 31570,
      "pct90Annual": 43590,
      "locationQuotient": 0.85
    },
    {
      "state": "Nebraska",
      "stateSlug": "nebraska",
      "stateAbbreviation": "NE",
      "totalEmployment": 100,
      "medianAnnual": 37030,
      "meanAnnual": 37270,
      "pct10Annual": 31340,
      "pct90Annual": 40230,
      "locationQuotient": 0.29
    },
    {
      "state": "Nevada",
      "stateSlug": "nevada",
      "stateAbbreviation": "NV",
      "totalEmployment": 380,
      "medianAnnual": 34560,
      "meanAnnual": 38040,
      "pct10Annual": 31930,
      "pct90Annual": 53030,
      "locationQuotient": 0.72
    },
    {
      "state": "New Hampshire",
      "stateSlug": "new-hampshire",
      "stateAbbreviation": "NH",
      "totalEmployment": 140,
      "medianAnnual": 39630,
      "meanAnnual": 41880,
      "pct10Annual": 37810,
      "pct90Annual": 46750,
      "locationQuotient": 0.59
    },
    {
      "state": "New Jersey",
      "stateSlug": "new-jersey",
      "stateAbbreviation": "NJ",
      "totalEmployment": 3530,
      "medianAnnual": 38140,
      "meanAnnual": 39110,
      "pct10Annual": 33190,
      "pct90Annual": 45180,
      "locationQuotient": 2.42
    },
    {
      "state": "New Mexico",
      "stateSlug": "new-mexico",
      "stateAbbreviation": "NM",
      "totalEmployment": 110,
      "medianAnnual": 36580,
      "meanAnnual": 36910,
      "pct10Annual": 34030,
      "pct90Annual": 38920,
      "locationQuotient": 0.38
    },
    {
      "state": "New York",
      "stateSlug": "new-york",
      "stateAbbreviation": "NY",
      "totalEmployment": 4210,
      "medianAnnual": 45600,
      "meanAnnual": 45460,
      "pct10Annual": 35990,
      "pct90Annual": 52620,
      "locationQuotient": 1.28
    },
    {
      "state": "North Carolina",
      "stateSlug": "north-carolina",
      "stateAbbreviation": "NC",
      "totalEmployment": 2040,
      "medianAnnual": 37200,
      "meanAnnual": 37820,
      "pct10Annual": 31800,
      "pct90Annual": 45700,
      "locationQuotient": 1.21
    },
    {
      "state": "Ohio",
      "stateSlug": "ohio",
      "stateAbbreviation": "OH",
      "totalEmployment": 2240,
      "medianAnnual": 36170,
      "meanAnnual": 36460,
      "pct10Annual": 32980,
      "pct90Annual": 41400,
      "locationQuotient": 1.18
    },
    {
      "state": "Oklahoma",
      "stateSlug": "oklahoma",
      "stateAbbreviation": "OK",
      "totalEmployment": 320,
      "medianAnnual": 33650,
      "meanAnnual": 34610,
      "pct10Annual": 29910,
      "pct90Annual": 37850,
      "locationQuotient": 0.54
    },
    {
      "state": "Oregon",
      "stateSlug": "oregon",
      "stateAbbreviation": "OR",
      "totalEmployment": 430,
      "medianAnnual": 43810,
      "meanAnnual": 44240,
      "pct10Annual": 38750,
      "pct90Annual": 48500,
      "locationQuotient": 0.64
    },
    {
      "state": "Pennsylvania",
      "stateSlug": "pennsylvania",
      "stateAbbreviation": "PA",
      "totalEmployment": 3750,
      "medianAnnual": 38790,
      "meanAnnual": 39540,
      "pct10Annual": 34310,
      "pct90Annual": 45600,
      "locationQuotient": 1.81
    },
    {
      "state": "Rhode Island",
      "stateSlug": "rhode-island",
      "stateAbbreviation": "RI",
      "totalEmployment": 230,
      "medianAnnual": 38660,
      "meanAnnual": 40550,
      "pct10Annual": 34370,
      "pct90Annual": 46840,
      "locationQuotient": 1.37
    },
    {
      "state": "South Carolina",
      "stateSlug": "south-carolina",
      "stateAbbreviation": "SC",
      "totalEmployment": 1940,
      "medianAnnual": 37440,
      "meanAnnual": 37710,
      "pct10Annual": 28690,
      "pct90Annual": 45060,
      "locationQuotient": 2.48
    },
    {
      "state": "South Dakota",
      "stateSlug": "south-dakota",
      "stateAbbreviation": "SD",
      "totalEmployment": 100,
      "medianAnnual": 30690,
      "meanAnnual": 36610,
      "pct10Annual": 27310,
      "pct90Annual": 48200,
      "locationQuotient": 0.63
    },
    {
      "state": "Tennessee",
      "stateSlug": "tennessee",
      "stateAbbreviation": "TN",
      "totalEmployment": 780,
      "medianAnnual": 37600,
      "meanAnnual": 37860,
      "pct10Annual": 29050,
      "pct90Annual": 44060,
      "locationQuotient": 0.69
    },
    {
      "state": "Texas",
      "stateSlug": "texas",
      "stateAbbreviation": "TX",
      "totalEmployment": 2360,
      "medianAnnual": 35840,
      "meanAnnual": 36190,
      "pct10Annual": 29640,
      "pct90Annual": 43230,
      "locationQuotient": 0.5
    },
    {
      "state": "Virginia",
      "stateSlug": "virginia",
      "stateAbbreviation": "VA",
      "totalEmployment": 1720,
      "medianAnnual": 36740,
      "meanAnnual": 45710,
      "pct10Annual": 30040,
      "pct90Annual": 79850,
      "locationQuotient": 1.23
    },
    {
      "state": "Washington",
      "stateSlug": "washington",
      "stateAbbreviation": "WA",
      "totalEmployment": 170,
      "medianAnnual": 51870,
      "meanAnnual": 51890,
      "pct10Annual": 44300,
      "pct90Annual": 62120,
      "locationQuotient": 0.14
    },
    {
      "state": "West Virginia",
      "stateSlug": "west-virginia",
      "stateAbbreviation": "WV",
      "totalEmployment": 250,
      "medianAnnual": 34630,
      "meanAnnual": 35770,
      "pct10Annual": 30450,
      "pct90Annual": 40170,
      "locationQuotient": 1.02
    },
    {
      "state": "Wisconsin",
      "stateSlug": "wisconsin",
      "stateAbbreviation": "WI",
      "totalEmployment": 710,
      "medianAnnual": 40090,
      "meanAnnual": 40320,
      "pct10Annual": 35660,
      "pct90Annual": 45830,
      "locationQuotient": 0.7
    },
    {
      "state": "Wyoming",
      "stateSlug": "wyoming",
      "stateAbbreviation": "WY",
      "totalEmployment": 50,
      "medianAnnual": 35400,
      "meanAnnual": 33100,
      "pct10Annual": 30400,
      "pct90Annual": 36300,
      "locationQuotient": 0.52
    }
  ]
}