{
  "title": "Property Appraisers and Assessors",
  "slug": "property-appraisers-and-assessors",
  "socCode": "13-2020",
  "dataYear": 2024,
  "typicalEducation": null,
  "workExperience": null,
  "onJobTraining": null,
  "jobOutlookPercent": null,
  "jobOutlookLabel": null,
  "national": {
    "totalEmployment": 59070,
    "meanHourly": 37.1,
    "meanAnnual": 77160,
    "medianHourly": 31.45,
    "medianAnnual": 65420,
    "pct10Hourly": 18.5,
    "pct25Hourly": 23.71,
    "pct75Hourly": 43.66,
    "pct90Hourly": 59.02,
    "pct10Annual": 38480,
    "pct25Annual": 49310,
    "pct75Annual": 90810,
    "pct90Annual": 122760
  },
  "states": [
    {
      "state": "Alabama",
      "stateSlug": "alabama",
      "stateAbbreviation": "AL",
      "totalEmployment": 540,
      "medianAnnual": 53050,
      "meanAnnual": 61630,
      "pct10Annual": 29490,
      "pct90Annual": 96710,
      "locationQuotient": 0.68
    },
    {
      "state": "Alaska",
      "stateSlug": "alaska",
      "stateAbbreviation": "AK",
      "totalEmployment": 150,
      "medianAnnual": 81540,
      "meanAnnual": 80650,
      "pct10Annual": 55190,
      "pct90Annual": 106300,
      "locationQuotient": 1.23
    },
    {
      "state": "Arizona",
      "stateSlug": "arizona",
      "stateAbbreviation": "AZ",
      "totalEmployment": 1210,
      "medianAnnual": 60050,
      "meanAnnual": 62660,
      "pct10Annual": 37960,
      "pct90Annual": 90810,
      "locationQuotient": 0.99
    },
    {
      "state": "Arkansas",
      "stateSlug": "arkansas",
      "stateAbbreviation": "AR",
      "totalEmployment": 900,
      "medianAnnual": 46590,
      "meanAnnual": 59220,
      "pct10Annual": 28250,
      "pct90Annual": 102980,
      "locationQuotient": 1.82
    },
    {
      "state": "California",
      "stateSlug": "california",
      "stateAbbreviation": "CA",
      "totalEmployment": 5660,
      "medianAnnual": 91400,
      "meanAnnual": 94750,
      "pct10Annual": 52150,
      "pct90Annual": 136150,
      "locationQuotient": 0.82
    },
    {
      "state": "Colorado",
      "stateSlug": "colorado",
      "stateAbbreviation": "CO",
      "totalEmployment": 1320,
      "medianAnnual": 64260,
      "meanAnnual": 80220,
      "pct10Annual": 47790,
      "pct90Annual": 130140,
      "locationQuotient": 1.19
    },
    {
      "state": "Connecticut",
      "stateSlug": "connecticut",
      "stateAbbreviation": "CT",
      "totalEmployment": 670,
      "medianAnnual": 84100,
      "meanAnnual": 94700,
      "pct10Annual": 58600,
      "pct90Annual": 139390,
      "locationQuotient": 1.03
    },
    {
      "state": "Delaware",
      "stateSlug": "delaware",
      "stateAbbreviation": "DE",
      "totalEmployment": 160,
      "medianAnnual": 57040,
      "meanAnnual": 68520,
      "pct10Annual": 42300,
      "pct90Annual": 137910,
      "locationQuotient": 0.9
    },
    {
      "state": "District of Columbia",
      "stateSlug": "district-of-columbia",
      "stateAbbreviation": "DC",
      "totalEmployment": 120,
      "medianAnnual": 105000,
      "meanAnnual": 105330,
      "pct10Annual": 73560,
      "pct90Annual": 142130,
      "locationQuotient": 0.42
    },
    {
      "state": "Florida",
      "stateSlug": "florida",
      "stateAbbreviation": "FL",
      "totalEmployment": 4090,
      "medianAnnual": 73010,
      "meanAnnual": 83730,
      "pct10Annual": 42030,
      "pct90Annual": 140380,
      "locationQuotient": 1.09
    },
    {
      "state": "Georgia",
      "stateSlug": "georgia",
      "stateAbbreviation": "GA",
      "totalEmployment": 2270,
      "medianAnnual": 49070,
      "meanAnnual": 57470,
      "pct10Annual": 28130,
      "pct90Annual": 88600,
      "locationQuotient": 1.22
    },
    {
      "state": "Hawaii",
      "stateSlug": "hawaii",
      "stateAbbreviation": "HI",
      "totalEmployment": 160,
      "medianAnnual": 68370,
      "meanAnnual": 74380,
      "pct10Annual": 49730,
      "pct90Annual": 105010,
      "locationQuotient": 0.66
    },
    {
      "state": "Idaho",
      "stateSlug": "idaho",
      "stateAbbreviation": "ID",
      "totalEmployment": 700,
      "medianAnnual": 68700,
      "meanAnnual": 78250,
      "pct10Annual": 36570,
      "pct90Annual": 131760,
      "locationQuotient": 2.15
    },
    {
      "state": "Illinois",
      "stateSlug": "illinois",
      "stateAbbreviation": "IL",
      "totalEmployment": 1840,
      "medianAnnual": null,
      "meanAnnual": null,
      "pct10Annual": null,
      "pct90Annual": null,
      "locationQuotient": 0.79
    },
    {
      "state": "Indiana",
      "stateSlug": "indiana",
      "stateAbbreviation": "IN",
      "totalEmployment": 2020,
      "medianAnnual": 61010,
      "meanAnnual": 62280,
      "pct10Annual": 37810,
      "pct90Annual": 93280,
      "locationQuotient": 1.65
    },
    {
      "state": "Iowa",
      "stateSlug": "iowa",
      "stateAbbreviation": "IA",
      "totalEmployment": 730,
      "medianAnnual": 79420,
      "meanAnnual": 91350,
      "pct10Annual": 41530,
      "pct90Annual": 155740,
      "locationQuotient": 1.22
    },
    {
      "state": "Kansas",
      "stateSlug": "kansas",
      "stateAbbreviation": "KS",
      "totalEmployment": 1120,
      "medianAnnual": 52870,
      "meanAnnual": 64860,
      "pct10Annual": 30650,
      "pct90Annual": 115160,
      "locationQuotient": 2.04
    },
    {
      "state": "Kentucky",
      "stateSlug": "kentucky",
      "stateAbbreviation": "KY",
      "totalEmployment": 320,
      "medianAnnual": 46910,
      "meanAnnual": 54650,
      "pct10Annual": 36600,
      "pct90Annual": 89840,
      "locationQuotient": 0.41
    },
    {
      "state": "Louisiana",
      "stateSlug": "louisiana",
      "stateAbbreviation": "LA",
      "totalEmployment": 500,
      "medianAnnual": 62710,
      "meanAnnual": 69570,
      "pct10Annual": 43600,
      "pct90Annual": 100130,
      "locationQuotient": 0.68
    },
    {
      "state": "Maine",
      "stateSlug": "maine",
      "stateAbbreviation": "ME",
      "totalEmployment": 270,
      "medianAnnual": 71100,
      "meanAnnual": 76320,
      "pct10Annual": 49930,
      "pct90Annual": 111190,
      "locationQuotient": 1.12
    },
    {
      "state": "Maryland",
      "stateSlug": "maryland",
      "stateAbbreviation": "MD",
      "totalEmployment": 560,
      "medianAnnual": 74760,
      "meanAnnual": 77370,
      "pct10Annual": 52230,
      "pct90Annual": 109990,
      "locationQuotient": 0.53
    },
    {
      "state": "Massachusetts",
      "stateSlug": "massachusetts",
      "stateAbbreviation": "MA",
      "totalEmployment": 1090,
      "medianAnnual": 87280,
      "meanAnnual": 90200,
      "pct10Annual": 50170,
      "pct90Annual": 129360,
      "locationQuotient": 0.78
    },
    {
      "state": "Michigan",
      "stateSlug": "michigan",
      "stateAbbreviation": "MI",
      "totalEmployment": 1920,
      "medianAnnual": 70520,
      "meanAnnual": 72710,
      "pct10Annual": 41180,
      "pct90Annual": 110660,
      "locationQuotient": 1.14
    },
    {
      "state": "Minnesota",
      "stateSlug": "minnesota",
      "stateAbbreviation": "MN",
      "totalEmployment": 1460,
      "medianAnnual": 78940,
      "meanAnnual": 85860,
      "pct10Annual": 51580,
      "pct90Annual": 137200,
      "locationQuotient": 1.3
    },
    {
      "state": "Mississippi",
      "stateSlug": "mississippi",
      "stateAbbreviation": "MS",
      "totalEmployment": 590,
      "medianAnnual": 49830,
      "meanAnnual": 55750,
      "pct10Annual": 32110,
      "pct90Annual": 87120,
      "locationQuotient": 1.33
    },
    {
      "state": "Missouri",
      "stateSlug": "missouri",
      "stateAbbreviation": "MO",
      "totalEmployment": 1650,
      "medianAnnual": 49040,
      "meanAnnual": 60030,
      "pct10Annual": 33390,
      "pct90Annual": 98020,
      "locationQuotient": 1.47
    },
    {
      "state": "Montana",
      "stateSlug": "montana",
      "stateAbbreviation": "MT",
      "totalEmployment": 260,
      "medianAnnual": 60990,
      "meanAnnual": 63490,
      "pct10Annual": 47310,
      "pct90Annual": 83330,
      "locationQuotient": 1.34
    },
    {
      "state": "Nebraska",
      "stateSlug": "nebraska",
      "stateAbbreviation": "NE",
      "totalEmployment": 450,
      "medianAnnual": 63370,
      "meanAnnual": 67620,
      "pct10Annual": 44220,
      "pct90Annual": 88660,
      "locationQuotient": 1.16
    },
    {
      "state": "Nevada",
      "stateSlug": "nevada",
      "stateAbbreviation": "NV",
      "totalEmployment": 690,
      "medianAnnual": 52000,
      "meanAnnual": 73630,
      "pct10Annual": 38650,
      "pct90Annual": 149520,
      "locationQuotient": 1.18
    },
    {
      "state": "New Hampshire",
      "stateSlug": "new-hampshire",
      "stateAbbreviation": "NH",
      "totalEmployment": 310,
      "medianAnnual": 69170,
      "meanAnnual": 76650,
      "pct10Annual": 45890,
      "pct90Annual": 122580,
      "locationQuotient": 1.2
    },
    {
      "state": "New Jersey",
      "stateSlug": "new-jersey",
      "stateAbbreviation": "NJ",
      "totalEmployment": 800,
      "medianAnnual": 89890,
      "meanAnnual": 96730,
      "pct10Annual": 37880,
      "pct90Annual": 155350,
      "locationQuotient": 0.49
    },
    {
      "state": "New Mexico",
      "stateSlug": "new-mexico",
      "stateAbbreviation": "NM",
      "totalEmployment": 630,
      "medianAnnual": 51860,
      "meanAnnual": 57770,
      "pct10Annual": 38110,
      "pct90Annual": 80090,
      "locationQuotient": 1.92
    },
    {
      "state": "New York",
      "stateSlug": "new-york",
      "stateAbbreviation": "NY",
      "totalEmployment": 3280,
      "medianAnnual": 77690,
      "meanAnnual": 88170,
      "pct10Annual": 50130,
      "pct90Annual": 132900,
      "locationQuotient": 0.9
    },
    {
      "state": "North Carolina",
      "stateSlug": "north-carolina",
      "stateAbbreviation": "NC",
      "totalEmployment": 2220,
      "medianAnnual": 56950,
      "meanAnnual": 65550,
      "pct10Annual": 36850,
      "pct90Annual": 107310,
      "locationQuotient": 1.19
    },
    {
      "state": "North Dakota",
      "stateSlug": "north-dakota",
      "stateAbbreviation": "ND",
      "totalEmployment": 320,
      "medianAnnual": 62340,
      "meanAnnual": 70410,
      "pct10Annual": 24700,
      "pct90Annual": 110500,
      "locationQuotient": 1.96
    },
    {
      "state": "Ohio",
      "stateSlug": "ohio",
      "stateAbbreviation": "OH",
      "totalEmployment": 1650,
      "medianAnnual": 73340,
      "meanAnnual": 71170,
      "pct10Annual": 37240,
      "pct90Annual": 103040,
      "locationQuotient": 0.78
    },
    {
      "state": "Oklahoma",
      "stateSlug": "oklahoma",
      "stateAbbreviation": "OK",
      "totalEmployment": 840,
      "medianAnnual": 48760,
      "meanAnnual": 54500,
      "pct10Annual": 35510,
      "pct90Annual": 80960,
      "locationQuotient": 1.3
    },
    {
      "state": "Oregon",
      "stateSlug": "oregon",
      "stateAbbreviation": "OR",
      "totalEmployment": 780,
      "medianAnnual": 66120,
      "meanAnnual": 70180,
      "pct10Annual": 36790,
      "pct90Annual": 105080,
      "locationQuotient": 1.03
    },
    {
      "state": "Pennsylvania",
      "stateSlug": "pennsylvania",
      "stateAbbreviation": "PA",
      "totalEmployment": 1520,
      "medianAnnual": 60320,
      "meanAnnual": 65340,
      "pct10Annual": 36700,
      "pct90Annual": 101340,
      "locationQuotient": 0.66
    },
    {
      "state": "Rhode Island",
      "stateSlug": "rhode-island",
      "stateAbbreviation": "RI",
      "totalEmployment": 130,
      "medianAnnual": 80460,
      "meanAnnual": 85470,
      "pct10Annual": 47800,
      "pct90Annual": 115400,
      "locationQuotient": 0.7
    },
    {
      "state": "South Carolina",
      "stateSlug": "south-carolina",
      "stateAbbreviation": "SC",
      "totalEmployment": 860,
      "medianAnnual": 59080,
      "meanAnnual": 60410,
      "pct10Annual": 38490,
      "pct90Annual": 94270,
      "locationQuotient": 0.99
    },
    {
      "state": "South Dakota",
      "stateSlug": "south-dakota",
      "stateAbbreviation": "SD",
      "totalEmployment": 450,
      "medianAnnual": 57440,
      "meanAnnual": 60960,
      "pct10Annual": 40130,
      "pct90Annual": 79610,
      "locationQuotient": 2.59
    },
    {
      "state": "Tennessee",
      "stateSlug": "tennessee",
      "stateAbbreviation": "TN",
      "totalEmployment": 1190,
      "medianAnnual": 61920,
      "meanAnnual": 68210,
      "pct10Annual": 39360,
      "pct90Annual": 107130,
      "locationQuotient": 0.95
    },
    {
      "state": "Texas",
      "stateSlug": "texas",
      "stateAbbreviation": "TX",
      "totalEmployment": 5520,
      "medianAnnual": 63960,
      "meanAnnual": 71260,
      "pct10Annual": 43180,
      "pct90Annual": 105930,
      "locationQuotient": 1.04
    },
    {
      "state": "Utah",
      "stateSlug": "utah",
      "stateAbbreviation": "UT",
      "totalEmployment": 770,
      "medianAnnual": 59920,
      "meanAnnual": 61930,
      "pct10Annual": 19600,
      "pct90Annual": 103730,
      "locationQuotient": 1.17
    },
    {
      "state": "Vermont",
      "stateSlug": "vermont",
      "stateAbbreviation": "VT",
      "totalEmployment": 240,
      "medianAnnual": 57900,
      "meanAnnual": 61020,
      "pct10Annual": 36160,
      "pct90Annual": 94390,
      "locationQuotient": 2.05
    },
    {
      "state": "Virginia",
      "stateSlug": "virginia",
      "stateAbbreviation": "VA",
      "totalEmployment": 1340,
      "medianAnnual": 73050,
      "meanAnnual": 75790,
      "pct10Annual": 44160,
      "pct90Annual": 115420,
      "locationQuotient": 0.86
    },
    {
      "state": "Washington",
      "stateSlug": "washington",
      "stateAbbreviation": "WA",
      "totalEmployment": 1190,
      "medianAnnual": 80120,
      "meanAnnual": 88720,
      "pct10Annual": 51330,
      "pct90Annual": 136490,
      "locationQuotient": 0.87
    },
    {
      "state": "West Virginia",
      "stateSlug": "west-virginia",
      "stateAbbreviation": "WV",
      "totalEmployment": 530,
      "medianAnnual": 45490,
      "meanAnnual": 48290,
      "pct10Annual": 30090,
      "pct90Annual": 65820,
      "locationQuotient": 1.96
    },
    {
      "state": "Wisconsin",
      "stateSlug": "wisconsin",
      "stateAbbreviation": "WI",
      "totalEmployment": 860,
      "medianAnnual": 64530,
      "meanAnnual": 75970,
      "pct10Annual": 37300,
      "pct90Annual": 106150,
      "locationQuotient": 0.77
    },
    {
      "state": "Wyoming",
      "stateSlug": "wyoming",
      "stateAbbreviation": "WY",
      "totalEmployment": 260,
      "medianAnnual": 62230,
      "meanAnnual": 61760,
      "pct10Annual": 36830,
      "pct90Annual": 84410,
      "locationQuotient": 2.41
    }
  ]
}